LICENSE
README.md
install.json
multiqc_jupyterlab.json
pyproject.toml
setup.cfg
setup.py
multiqc_jupyterlab/__init__.py
multiqc_jupyterlab/_frontend.py
multiqc_jupyterlab/_version.py
multiqc_jupyterlab/multiqc_extension.py
multiqc_jupyterlab.egg-info/PKG-INFO
multiqc_jupyterlab.egg-info/SOURCES.txt
multiqc_jupyterlab.egg-info/dependency_links.txt
multiqc_jupyterlab.egg-info/requires.txt
multiqc_jupyterlab.egg-info/top_level.txt
multiqc_jupyterlab/labextension/install.json
multiqc_jupyterlab/labextension/package.json
multiqc_jupyterlab/labextension/static/480.d1b0f31ee77ba0981970.js
multiqc_jupyterlab/labextension/static/568.4b4e409f4fd1381a6b64.js
multiqc_jupyterlab/labextension/static/remoteEntry.97594b8c840788614a4a.js
multiqc_jupyterlab/labextension/static/style.js
multiqc_jupyterlab/labextension/static/third-party-licenses.json
multiqc_jupyterlab/nbextension/extension.js
multiqc_jupyterlab/nbextension/index.js
multiqc_jupyterlab/nbextension/index.js.map
multiqc_jupyterlab/tests/__init__.py
multiqc_jupyterlab/tests/conftest.py