Metadata-Version: 2.1
Name: multiqc-jupyterlab
Version: 0.3.4
Summary: JupyterLab extension for MultiQC
Home-page: https://github.com/olkuka/multiqc_jupyterlab
Author: Aleksandra Kukawka
Author-email: 01143587@pw.edu.pl
License: GPLv3
Keywords: Jupyter,Widgets,IPython
Platform: Linux
Platform: Mac OS X
Platform: Windows
Classifier: Intended Audience :: Developers
Classifier: Intended Audience :: Science/Research
Classifier: License :: OSI Approved :: BSD License
Classifier: Programming Language :: Python
Classifier: Programming Language :: Python :: 3
Classifier: Programming Language :: Python :: 3.4
Classifier: Programming Language :: Python :: 3.5
Classifier: Programming Language :: Python :: 3.6
Classifier: Programming Language :: Python :: 3.7
Classifier: Framework :: Jupyter
Requires-Python: >=3.6
Provides-Extra: test
Provides-Extra: examples
Provides-Extra: docs
License-File: LICENSE
